.gitignore
.gitmodules
.pre-commit-config.yaml
CMakeLists.txt
LICENSE
MANIFEST.in
README.md
pyproject.toml
requirements.txt
setup.py
.github/workflows/conda.yml
.github/workflows/python-package.yml
.github/workflows/python-publish.yml
cmake/FindFFTW.cmake
conda/environment.yaml
conda/meta.yaml
include/guanaco/config.h
include/guanaco/constants.h
include/guanaco/correct.h
include/guanaco/ctf.h
include/guanaco/error.h
include/guanaco/fft.h
include/guanaco/filter.h
include/guanaco/guanaco.h
include/guanaco/reconstructor.h
include/guanaco/system.h
pybind11/.appveyor.yml
pybind11/.clang-format
pybind11/.clang-tidy
pybind11/.cmake-format.yaml
pybind11/.codespell-ignore-lines
pybind11/.git
pybind11/.gitattributes
pybind11/.gitignore
pybind11/.pre-commit-config.yaml
pybind11/.readthedocs.yml
pybind11/CMakeLists.txt
pybind11/LICENSE
pybind11/MANIFEST.in
pybind11/README.rst
pybind11/SECURITY.md
pybind11/noxfile.py
pybind11/pyproject.toml
pybind11/setup.cfg
pybind11/setup.py
pybind11/.github/CODEOWNERS
pybind11/.github/CONTRIBUTING.md
pybind11/.github/dependabot.yml
pybind11/.github/labeler.yml
pybind11/.github/labeler_merged.yml
pybind11/.github/pull_request_template.md
pybind11/.github/ISSUE_TEMPLATE/bug-report.yml
pybind11/.github/ISSUE_TEMPLATE/config.yml
pybind11/.github/matchers/pylint.json
pybind11/.github/workflows/ci.yml
pybind11/.github/workflows/configure.yml
pybind11/.github/workflows/format.yml
pybind11/.github/workflows/labeler.yml
pybind11/.github/workflows/pip.yml
pybind11/.github/workflows/upstream.yml
pybind11/docs/Doxyfile
pybind11/docs/Makefile
pybind11/docs/basics.rst
pybind11/docs/benchmark.py
pybind11/docs/benchmark.rst
pybind11/docs/changelog.rst
pybind11/docs/classes.rst
pybind11/docs/compiling.rst
pybind11/docs/conf.py
pybind11/docs/faq.rst
pybind11/docs/index.rst
pybind11/docs/installing.rst
pybind11/docs/limitations.rst
pybind11/docs/pybind11-logo.png
pybind11/docs/pybind11_vs_boost_python1.png
pybind11/docs/pybind11_vs_boost_python1.svg
src/guanaco.egg-info/PKG-INFO
src/guanaco.egg-info/SOURCES.txt
src/guanaco.egg-info/dependency_links.txt
src/guanaco.egg-info/entry_points.txt
src/guanaco.egg-info/requires.txt
src/guanaco.egg-info/top_level.txt
