Metadata-Version: 2.4
Name: guanaco
Version: 0.3.4
Summary: 3D CTF correction
Author-email: James Parkhurst <james.parkhurst@rfi.ac.uk>
License-Expression: GPL-3.0-or-later
Project-URL: Source, https://github.com/rosalindfranklininstitute/guanaco
Project-URL: Tracker, https://github.com/rosalindfranklininstitute/guanaco/issues
Keywords: Tomography
Classifier: Development Status :: 4 - Beta
Classifier: Programming Language :: Python :: 3
Classifier: Programming Language :: Python :: 3.6
Classifier: Programming Language :: Python :: 3.7
Classifier: Programming Language :: Python :: 3.8
Classifier: Programming Language :: Python :: 3.9
Classifier: Programming Language :: Python :: 3.10
Classifier: Programming Language :: Python :: 3.11
License-File: LICENSE
Requires-Dist: mrcfile
Requires-Dist: numpy
Requires-Dist: pyyaml
Provides-Extra: build-sphinx
Requires-Dist: sphinx; extra == "build-sphinx"
Requires-Dist: sphinx_rtd_theme; extra == "build-sphinx"
Dynamic: license-file
Dynamic: provides-extra
Dynamic: requires-dist
